{
    "dataset_id": "503d7e35-a2cd-4d98-a272-930519fc29b5",
    "folder": {
        "id": "479c24a2-d399-4074-b47f-7c82c51a95d8",
        "name": "RBGE"
    },
    "image": {
        "id": "203774cc-9d52-4de3-bc87-635cfd14925e",
        "iiif_base_url": "https://europe-gamma.iiif.teklia.com/iiif/2/synthesys%2Fmlb-data%2Fsynthesys%2Fherbarium_2%2FE00759729.jpg",
        "url": "https://europe-gamma.iiif.teklia.com/iiif/2/synthesys%2Fmlb-data%2Fsynthesys%2Fherbarium_2%2FE00759729.jpg/full/full/0/default.jpg"
    },
    "page": {
        "id": "65a2158e-b7a6-459b-873f-dce8707b0e19",
        "name": "E00759729",
        "rotation_angle": 0
    },
    "polygons": {
        "text_line": [
            [
                [
                    213,
                    3051
                ],
                [
                    213,
                    3278
                ],
                [
                    1886,
                    3278
                ],
                [
                    1886,
                    3051
                ],
                [
                    213,
                    3051
                ]
            ],
            [
                [
                    254,
                    3317
                ],
                [
                    254,
                    3466
                ],
                [
                    1785,
                    3466
                ],
                [
                    1785,
                    3317
                ],
                [
                    254,
                    3317
                ]
            ],
            [
                [
                    1893,
                    3147
                ],
                [
                    1893,
                    3258
                ],
                [
                    2969,
                    3258
                ],
                [
                    2969,
                    3147
                ],
                [
                    1893,
                    3147
                ]
            ],
            [
                [
                    2033,
                    3270
                ],
                [
                    2033,
                    3383
                ],
                [
                    3166,
                    3383
                ],
                [
                    3166,
                    3270
                ],
                [
                    2033,
                    3270
                ]
            ],
            [
                [
                    1914,
                    3392
                ],
                [
                    1914,
                    3467
                ],
                [
                    3079,
                    3467
                ],
                [
                    3079,
                    3392
                ],
                [
                    1914,
                    3392
                ]
            ],
            [
                [
                    2183,
                    3473
                ],
                [
                    2183,
                    3554
                ],
                [
                    2559,
                    3554
                ],
                [
                    2559,
                    3473
                ],
                [
                    2183,
                    3473
                ]
            ],
            [
                [
                    4216,
                    3638
                ],
                [
                    4216,
                    3818
                ],
                [
                    4697,
                    3818
                ],
                [
                    4697,
                    3638
                ],
                [
                    4216,
                    3638
                ]
            ],
            [
                [
                    3857,
                    4098
                ],
                [
                    3907,
                    4284
                ],
                [
                    4642,
                    3994
                ],
                [
                    4540,
                    3863
                ],
                [
                    3863,
                    4098
                ],
                [
                    3857,
                    4098
                ]
            ],
            [
                [
                    4145,
                    4242
                ],
                [
                    4145,
                    4300
                ],
                [
                    4804,
                    4328
                ],
                [
                    4809,
                    4276
                ],
                [
                    4150,
                    4239
                ],
                [
                    4145,
                    4242
                ]
            ],
            [
                [
                    4315,
                    4357
                ],
                [
                    4639,
                    4370
                ],
                [
                    4642,
                    4328
                ],
                [
                    4320,
                    4313
                ],
                [
                    4318,
                    4307
                ],
                [
                    4315,
                    4357
                ]
            ],
            [
                [
                    4318,
                    4574
                ],
                [
                    4608,
                    4590
                ],
                [
                    4605,
                    4537
                ],
                [
                    4339,
                    4519
                ],
                [
                    4333,
                    4517
                ],
                [
                    4318,
                    4574
                ]
            ],
            [
                [
                    3835,
                    5195
                ],
                [
                    3835,
                    5371
                ],
                [
                    4887,
                    5371
                ],
                [
                    4887,
                    5195
                ],
                [
                    3835,
                    5195
                ]
            ],
            [
                [
                    3835,
                    6065
                ],
                [
                    3835,
                    6169
                ],
                [
                    4322,
                    6169
                ],
                [
                    4322,
                    6065
                ],
                [
                    3835,
                    6065
                ]
            ],
            [
                [
                    2759,
                    6400
                ],
                [
                    2759,
                    6546
                ],
                [
                    4133,
                    6546
                ],
                [
                    4133,
                    6400
                ],
                [
                    2759,
                    6400
                ]
            ],
            [
                [
                    4175,
                    6453
                ],
                [
                    4175,
                    6615
                ],
                [
                    4725,
                    6615
                ],
                [
                    4725,
                    6453
                ],
                [
                    4175,
                    6453
                ]
            ],
            [
                [
                    2962,
                    6570
                ],
                [
                    2962,
                    6672
                ],
                [
                    3891,
                    6672
                ],
                [
                    3891,
                    6570
                ],
                [
                    2962,
                    6570
                ]
            ],
            [
                [
                    3554,
                    6680
                ],
                [
                    3554,
                    6833
                ],
                [
                    4223,
                    6833
                ],
                [
                    4223,
                    6680
                ],
                [
                    3554,
                    6680
                ]
            ],
            [
                [
                    2777,
                    6857
                ],
                [
                    2777,
                    6955
                ],
                [
                    3446,
                    6955
                ],
                [
                    3446,
                    6857
                ],
                [
                    2777,
                    6857
                ]
            ],
            [
                [
                    2786,
                    6973
                ],
                [
                    2786,
                    7132
                ],
                [
                    4647,
                    7132
                ],
                [
                    4647,
                    6973
                ],
                [
                    2786,
                    6973
                ]
            ],
            [
                [
                    2845,
                    7147
                ],
                [
                    2845,
                    7362
                ],
                [
                    4453,
                    7362
                ],
                [
                    4453,
                    7147
                ],
                [
                    2845,
                    7147
                ]
            ],
            [
                [
                    2786,
                    7458
                ],
                [
                    2786,
                    7589
                ],
                [
                    4734,
                    7589
                ],
                [
                    4734,
                    7458
                ],
                [
                    2786,
                    7458
                ]
            ],
            [
                [
                    2821,
                    7601
                ],
                [
                    2821,
                    7703
                ],
                [
                    3829,
                    7703
                ],
                [
                    3829,
                    7601
                ],
                [
                    2821,
                    7601
                ]
            ],
            [
                [
                    2884,
                    7718
                ],
                [
                    2884,
                    7834
                ],
                [
                    4139,
                    7834
                ],
                [
                    4139,
                    7718
                ],
                [
                    2884,
                    7718
                ]
            ],
            [
                [
                    1647,
                    7723
                ],
                [
                    1647,
                    7810
                ],
                [
                    2083,
                    7810
                ],
                [
                    2083,
                    7723
                ],
                [
                    1647,
                    7723
                ]
            ],
            [
                [
                    1019,
                    7843
                ],
                [
                    1019,
                    7959
                ],
                [
                    2600,
                    7959
                ],
                [
                    2600,
                    7843
                ],
                [
                    1019,
                    7843
                ]
            ],
            [
                [
                    989,
                    8004
                ],
                [
                    989,
                    8156
                ],
                [
                    2663,
                    8156
                ],
                [
                    2663,
                    8004
                ],
                [
                    989,
                    8004
                ]
            ],
            [
                [
                    126,
                    7762
                ],
                [
                    777,
                    7746
                ],
                [
                    777,
                    7693
                ],
                [
                    130,
                    7712
                ],
                [
                    134,
                    7706
                ],
                [
                    126,
                    7762
                ]
            ],
            [
                [
                    291,
                    7804
                ],
                [
                    603,
                    7794
                ],
                [
                    607,
                    7756
                ],
                [
                    302,
                    7762
                ],
                [
                    298,
                    7760
                ],
                [
                    291,
                    7804
                ]
            ],
            [
                [
                    296,
                    8024
                ],
                [
                    622,
                    8015
                ],
                [
                    628,
                    7959
                ],
                [
                    306,
                    7965
                ],
                [
                    302,
                    7959
                ],
                [
                    296,
                    8024
                ]
            ]
        ]
    }
}