{
    "dataset_id": "503d7e35-a2cd-4d98-a272-930519fc29b5",
    "folder": {
        "id": "40737841-bfc1-4187-b1f6-3328e53d3aa3",
        "name": "MeiseBG"
    },
    "image": {
        "id": "aa1cffe9-24d4-4d50-951f-d7a14d1fbd04",
        "iiif_base_url": "https://europe-gamma.iiif.teklia.com/iiif/2/synthesys%2Fmlb-data%2Fsynthesys%2Fherbarium_2%2FBR0000008631558.jpg",
        "url": "https://europe-gamma.iiif.teklia.com/iiif/2/synthesys%2Fmlb-data%2Fsynthesys%2Fherbarium_2%2FBR0000008631558.jpg/full/full/0/default.jpg"
    },
    "page": {
        "id": "55ec559c-2ae5-4af5-a519-33d6344fcd09",
        "name": "BR0000008631558",
        "rotation_angle": 0
    },
    "polygons": {
        "text_line": [
            [
                [
                    5350,
                    8567
                ],
                [
                    5354,
                    8575
                ],
                [
                    5405,
                    8802
                ],
                [
                    6148,
                    8597
                ],
                [
                    6144,
                    8453
                ],
                [
                    5350,
                    8567
                ]
            ],
            [
                [
                    4060,
                    9254
                ],
                [
                    4097,
                    9409
                ],
                [
                    5475,
                    9398
                ],
                [
                    5504,
                    9482
                ],
                [
                    5545,
                    9497
                ],
                [
                    5596,
                    9398
                ],
                [
                    6085,
                    9445
                ],
                [
                    6125,
                    9262
                ],
                [
                    4068,
                    9247
                ],
                [
                    4060,
                    9254
                ]
            ],
            [
                [
                    4229,
                    9423
                ],
                [
                    4233,
                    9438
                ],
                [
                    4281,
                    9581
                ],
                [
                    5427,
                    9556
                ],
                [
                    5809,
                    9570
                ],
                [
                    5854,
                    9493
                ],
                [
                    5662,
                    9409
                ],
                [
                    5600,
                    9409
                ],
                [
                    5549,
                    9512
                ],
                [
                    5497,
                    9497
                ],
                [
                    5457,
                    9405
                ],
                [
                    4229,
                    9423
                ]
            ],
            [
                [
                    4079,
                    9662
                ],
                [
                    4082,
                    9743
                ],
                [
                    5141,
                    9758
                ],
                [
                    5861,
                    9761
                ],
                [
                    5887,
                    9633
                ],
                [
                    5512,
                    9567
                ],
                [
                    5387,
                    9563
                ],
                [
                    4082,
                    9640
                ],
                [
                    4079,
                    9662
                ]
            ],
            [
                [
                    4317,
                    8946
                ],
                [
                    4317,
                    9052
                ],
                [
                    5710,
                    9052
                ],
                [
                    5710,
                    8946
                ],
                [
                    4317,
                    8946
                ]
            ],
            [
                [
                    4817,
                    9085
                ],
                [
                    4817,
                    9151
                ],
                [
                    5199,
                    9151
                ],
                [
                    5199,
                    9085
                ],
                [
                    4817,
                    9085
                ]
            ],
            [
                [
                    3950,
                    9876
                ],
                [
                    3950,
                    10159
                ],
                [
                    5971,
                    10159
                ],
                [
                    5971,
                    9876
                ],
                [
                    3950,
                    9876
                ]
            ],
            [
                [
                    3303,
                    8446
                ],
                [
                    3303,
                    8747
                ],
                [
                    4196,
                    8747
                ],
                [
                    4196,
                    8446
                ],
                [
                    3303,
                    8446
                ]
            ],
            [
                [
                    2837,
                    8934
                ],
                [
                    2837,
                    9122
                ],
                [
                    3333,
                    9122
                ],
                [
                    3333,
                    8934
                ],
                [
                    2837,
                    8934
                ]
            ],
            [
                [
                    2609,
                    9144
                ],
                [
                    2609,
                    9151
                ],
                [
                    2646,
                    9269
                ],
                [
                    3329,
                    9258
                ],
                [
                    3498,
                    9306
                ],
                [
                    3752,
                    9225
                ],
                [
                    3789,
                    9170
                ],
                [
                    3531,
                    9041
                ],
                [
                    3483,
                    9133
                ],
                [
                    2609,
                    9144
                ]
            ],
            [
                [
                    2539,
                    9364
                ],
                [
                    2587,
                    9497
                ],
                [
                    3274,
                    9533
                ],
                [
                    3531,
                    9489
                ],
                [
                    3891,
                    9445
                ],
                [
                    3906,
                    9276
                ],
                [
                    3708,
                    9265
                ],
                [
                    3502,
                    9324
                ],
                [
                    3219,
                    9313
                ],
                [
                    2546,
                    9357
                ],
                [
                    2539,
                    9364
                ]
            ],
            [
                [
                    1380,
                    8478
                ],
                [
                    1391,
                    8559
                ],
                [
                    1998,
                    8541
                ],
                [
                    2097,
                    8519
                ],
                [
                    2079,
                    8430
                ],
                [
                    1380,
                    8478
                ]
            ],
            [
                [
                    1384,
                    8666
                ],
                [
                    2112,
                    8621
                ],
                [
                    2115,
                    8548
                ],
                [
                    1388,
                    8577
                ],
                [
                    1388,
                    8581
                ],
                [
                    1384,
                    8666
                ]
            ],
            [
                [
                    1667,
                    8750
                ],
                [
                    1851,
                    8732
                ],
                [
                    1844,
                    8647
                ],
                [
                    1671,
                    8662
                ],
                [
                    1671,
                    8669
                ],
                [
                    1667,
                    8750
                ]
            ],
            [
                [
                    1002,
                    8919
                ],
                [
                    1013,
                    8937
                ],
                [
                    1017,
                    9037
                ],
                [
                    2340,
                    8963
                ],
                [
                    2336,
                    8835
                ],
                [
                    1002,
                    8919
                ]
            ],
            [
                [
                    1836,
                    9007
                ],
                [
                    1836,
                    9022
                ],
                [
                    1836,
                    9132
                ],
                [
                    2248,
                    9107
                ],
                [
                    2237,
                    8985
                ],
                [
                    1836,
                    9007
                ]
            ],
            [
                [
                    1777,
                    9231
                ],
                [
                    1785,
                    9239
                ],
                [
                    1785,
                    9353
                ],
                [
                    2329,
                    9312
                ],
                [
                    2329,
                    9184
                ],
                [
                    1777,
                    9231
                ]
            ],
            [
                [
                    951,
                    9478
                ],
                [
                    1763,
                    9419
                ],
                [
                    1763,
                    9349
                ],
                [
                    958,
                    9390
                ],
                [
                    965,
                    9390
                ],
                [
                    951,
                    9478
                ]
            ]
        ]
    }
}