{
    "dataset_id": "503d7e35-a2cd-4d98-a272-930519fc29b5",
    "folder": {
        "id": "438d96cb-88a1-4786-a83a-08301ba7e92a",
        "name": "BGBM"
    },
    "image": {
        "id": "936f9e6e-3440-4015-9ff0-302878695f40",
        "iiif_base_url": "https://europe-gamma.iiif.teklia.com/iiif/2/synthesys%2Fmlb-data%2Fsynthesys%2Fherbarium_2%2FB_10_0067092.jpg",
        "url": "https://europe-gamma.iiif.teklia.com/iiif/2/synthesys%2Fmlb-data%2Fsynthesys%2Fherbarium_2%2FB_10_0067092.jpg/full/full/0/default.jpg"
    },
    "page": {
        "id": "176bce76-b4f3-4ae3-83ef-d04f6e5ed3bc",
        "name": "B_10_0067092",
        "rotation_angle": 0
    },
    "polygons": {
        "text_line": [
            [
                [
                    3706,
                    9323
                ],
                [
                    3706,
                    9462
                ],
                [
                    4319,
                    9462
                ],
                [
                    4319,
                    9323
                ],
                [
                    3706,
                    9323
                ]
            ],
            [
                [
                    4933,
                    9272
                ],
                [
                    5672,
                    9264
                ],
                [
                    5643,
                    9142
                ],
                [
                    4941,
                    9142
                ],
                [
                    4933,
                    9272
                ]
            ],
            [
                [
                    5067,
                    9415
                ],
                [
                    5067,
                    9478
                ],
                [
                    5513,
                    9478
                ],
                [
                    5513,
                    9415
                ],
                [
                    5067,
                    9415
                ]
            ],
            [
                [
                    929,
                    7924
                ],
                [
                    929,
                    8059
                ],
                [
                    2113,
                    8059
                ],
                [
                    2113,
                    7924
                ],
                [
                    929,
                    7924
                ]
            ],
            [
                [
                    1240,
                    8231
                ],
                [
                    1240,
                    8353
                ],
                [
                    2122,
                    8353
                ],
                [
                    2122,
                    8231
                ],
                [
                    1240,
                    8231
                ]
            ],
            [
                [
                    324,
                    8773
                ],
                [
                    324,
                    8857
                ],
                [
                    2231,
                    8857
                ],
                [
                    2231,
                    8773
                ],
                [
                    324,
                    8773
                ]
            ],
            [
                [
                    324,
                    8860
                ],
                [
                    328,
                    8931
                ],
                [
                    2189,
                    8927
                ],
                [
                    2190,
                    8860
                ],
                [
                    324,
                    8860
                ]
            ],
            [
                [
                    334,
                    8932
                ],
                [
                    336,
                    9005
                ],
                [
                    1769,
                    9003
                ],
                [
                    1770,
                    8932
                ],
                [
                    334,
                    8932
                ]
            ],
            [
                [
                    238,
                    9222
                ],
                [
                    238,
                    9366
                ],
                [
                    1650,
                    9366
                ],
                [
                    1650,
                    9222
                ],
                [
                    238,
                    9222
                ]
            ],
            [
                [
                    1914,
                    9138
                ],
                [
                    1914,
                    9287
                ],
                [
                    2519,
                    9287
                ],
                [
                    2519,
                    9138
                ],
                [
                    1914,
                    9138
                ]
            ],
            [
                [
                    2043,
                    9048
                ],
                [
                    2399,
                    9045
                ],
                [
                    2405,
                    8924
                ],
                [
                    2049,
                    8922
                ],
                [
                    2043,
                    9048
                ]
            ]
        ]
    }
}