{
    "dataset_id": "503d7e35-a2cd-4d98-a272-930519fc29b5",
    "folder": {
        "id": "438d96cb-88a1-4786-a83a-08301ba7e92a",
        "name": "BGBM"
    },
    "image": {
        "id": "f4fc2041-8eb9-4814-bee3-9becf78eae72",
        "iiif_base_url": "https://europe-gamma.iiif.teklia.com/iiif/2/synthesys%2Fmlb-data%2Fsynthesys%2Fherbarium_2%2FB_10_0057440.jpg",
        "url": "https://europe-gamma.iiif.teklia.com/iiif/2/synthesys%2Fmlb-data%2Fsynthesys%2Fherbarium_2%2FB_10_0057440.jpg/full/full/0/default.jpg"
    },
    "page": {
        "id": "4a351525-4a1d-44e2-a53a-b50768332ce9",
        "name": "B_10_0057440",
        "rotation_angle": 0
    },
    "polygons": {
        "text_line": [
            [
                [
                    29,
                    3690
                ],
                [
                    953,
                    3667
                ],
                [
                    950,
                    3620
                ],
                [
                    36,
                    3644
                ],
                [
                    29,
                    3690
                ]
            ],
            [
                [
                    35,
                    3691
                ],
                [
                    38,
                    3725
                ],
                [
                    490,
                    3710
                ],
                [
                    484,
                    3680
                ],
                [
                    38,
                    3691
                ],
                [
                    35,
                    3691
                ]
            ],
            [
                [
                    33,
                    3818
                ],
                [
                    559,
                    3800
                ],
                [
                    558,
                    3736
                ],
                [
                    36,
                    3755
                ],
                [
                    36,
                    3757
                ],
                [
                    33,
                    3818
                ]
            ],
            [
                [
                    522,
                    3730
                ],
                [
                    522,
                    3805
                ],
                [
                    565,
                    3805
                ],
                [
                    565,
                    3730
                ],
                [
                    522,
                    3730
                ]
            ],
            [
                [
                    237,
                    3914
                ],
                [
                    237,
                    3998
                ],
                [
                    522,
                    3987
                ],
                [
                    526,
                    4005
                ],
                [
                    571,
                    4005
                ],
                [
                    614,
                    3908
                ],
                [
                    241,
                    3914
                ],
                [
                    237,
                    3914
                ]
            ],
            [
                [
                    100,
                    4075
                ],
                [
                    162,
                    4073
                ],
                [
                    162,
                    4109
                ],
                [
                    202,
                    4112
                ],
                [
                    241,
                    4064
                ],
                [
                    389,
                    4064
                ],
                [
                    560,
                    4058
                ],
                [
                    578,
                    4045
                ],
                [
                    601,
                    4054
                ],
                [
                    627,
                    4054
                ],
                [
                    640,
                    4035
                ],
                [
                    668,
                    4026
                ],
                [
                    730,
                    3996
                ],
                [
                    770,
                    3955
                ],
                [
                    755,
                    3932
                ],
                [
                    713,
                    3938
                ],
                [
                    648,
                    3994
                ],
                [
                    627,
                    3981
                ],
                [
                    590,
                    3998
                ],
                [
                    567,
                    4026
                ],
                [
                    177,
                    4028
                ],
                [
                    190,
                    3985
                ],
                [
                    115,
                    3985
                ],
                [
                    110,
                    3983
                ],
                [
                    100,
                    4075
                ]
            ],
            [
                [
                    192,
                    4118
                ],
                [
                    198,
                    4122
                ],
                [
                    217,
                    4125
                ],
                [
                    232,
                    4135
                ],
                [
                    260,
                    4112
                ],
                [
                    530,
                    4105
                ],
                [
                    530,
                    4122
                ],
                [
                    560,
                    4118
                ],
                [
                    575,
                    4095
                ],
                [
                    715,
                    4090
                ],
                [
                    736,
                    4035
                ],
                [
                    644,
                    4037
                ],
                [
                    610,
                    4058
                ],
                [
                    578,
                    4047
                ],
                [
                    556,
                    4060
                ],
                [
                    245,
                    4067
                ],
                [
                    192,
                    4118
                ]
            ],
            [
                [
                    10,
                    4214
                ],
                [
                    22,
                    4240
                ],
                [
                    95,
                    4172
                ],
                [
                    605,
                    4161
                ],
                [
                    584,
                    4182
                ],
                [
                    610,
                    4187
                ],
                [
                    646,
                    4167
                ],
                [
                    815,
                    4167
                ],
                [
                    848,
                    4084
                ],
                [
                    586,
                    4107
                ],
                [
                    569,
                    4124
                ],
                [
                    532,
                    4125
                ],
                [
                    515,
                    4112
                ],
                [
                    260,
                    4116
                ],
                [
                    235,
                    4137
                ],
                [
                    211,
                    4137
                ],
                [
                    164,
                    4133
                ],
                [
                    138,
                    4107
                ],
                [
                    74,
                    4109
                ],
                [
                    72,
                    4110
                ],
                [
                    10,
                    4214
                ]
            ],
            [
                [
                    172,
                    4279
                ],
                [
                    672,
                    4242
                ],
                [
                    721,
                    4180
                ],
                [
                    650,
                    4174
                ],
                [
                    620,
                    4195
                ],
                [
                    575,
                    4195
                ],
                [
                    590,
                    4167
                ],
                [
                    190,
                    4184
                ],
                [
                    190,
                    4182
                ],
                [
                    172,
                    4279
                ]
            ],
            [
                [
                    427,
                    4253
                ],
                [
                    494,
                    4270
                ],
                [
                    507,
                    4307
                ],
                [
                    605,
                    4332
                ],
                [
                    618,
                    4294
                ],
                [
                    667,
                    4307
                ],
                [
                    700,
                    4294
                ],
                [
                    738,
                    4264
                ],
                [
                    438,
                    4206
                ],
                [
                    436,
                    4206
                ],
                [
                    427,
                    4253
                ]
            ],
            [
                [
                    217,
                    4408
                ],
                [
                    768,
                    4384
                ],
                [
                    805,
                    4279
                ],
                [
                    732,
                    4274
                ],
                [
                    670,
                    4313
                ],
                [
                    607,
                    4335
                ],
                [
                    520,
                    4313
                ],
                [
                    479,
                    4313
                ],
                [
                    410,
                    4279
                ],
                [
                    258,
                    4285
                ],
                [
                    256,
                    4283
                ],
                [
                    217,
                    4408
                ]
            ],
            [
                [
                    1774,
                    4066
                ],
                [
                    1774,
                    4130
                ],
                [
                    2033,
                    4130
                ],
                [
                    2033,
                    4066
                ],
                [
                    1774,
                    4066
                ]
            ],
            [
                [
                    1770,
                    4149
                ],
                [
                    1770,
                    4205
                ],
                [
                    2039,
                    4205
                ],
                [
                    2039,
                    4149
                ],
                [
                    1770,
                    4149
                ]
            ],
            [
                [
                    1742,
                    4323
                ],
                [
                    2057,
                    4330
                ],
                [
                    2057,
                    4289
                ],
                [
                    1744,
                    4280
                ],
                [
                    1748,
                    4276
                ],
                [
                    1742,
                    4323
                ]
            ],
            [
                [
                    1798,
                    4398
                ],
                [
                    1798,
                    4428
                ],
                [
                    1995,
                    4435
                ],
                [
                    2001,
                    4404
                ],
                [
                    1798,
                    4398
                ]
            ],
            [
                [
                    2378,
                    4372
                ],
                [
                    2380,
                    4372
                ],
                [
                    2382,
                    4454
                ],
                [
                    2755,
                    4447
                ],
                [
                    2755,
                    4370
                ],
                [
                    2378,
                    4372
                ]
            ],
            [
                [
                    2367,
                    4338
                ],
                [
                    2800,
                    4338
                ],
                [
                    2798,
                    4282
                ],
                [
                    2369,
                    4280
                ],
                [
                    2371,
                    4280
                ],
                [
                    2367,
                    4338
                ]
            ],
            [
                [
                    2703,
                    3925
                ],
                [
                    2703,
                    4004
                ],
                [
                    2748,
                    4004
                ],
                [
                    2748,
                    3925
                ],
                [
                    2703,
                    3925
                ]
            ],
            [
                [
                    2637,
                    3967
                ],
                [
                    2637,
                    4004
                ],
                [
                    2688,
                    4004
                ],
                [
                    2688,
                    3967
                ],
                [
                    2637,
                    3967
                ]
            ],
            [
                [
                    2637,
                    3864
                ],
                [
                    2637,
                    3899
                ],
                [
                    2691,
                    3899
                ],
                [
                    2691,
                    3864
                ],
                [
                    2637,
                    3864
                ]
            ],
            [
                [
                    2637,
                    3755
                ],
                [
                    2637,
                    3796
                ],
                [
                    2691,
                    3796
                ],
                [
                    2691,
                    3755
                ],
                [
                    2637,
                    3755
                ]
            ],
            [
                [
                    2637,
                    3651
                ],
                [
                    2637,
                    3694
                ],
                [
                    2680,
                    3694
                ],
                [
                    2680,
                    3651
                ],
                [
                    2637,
                    3651
                ]
            ],
            [
                [
                    2639,
                    3545
                ],
                [
                    2639,
                    3593
                ],
                [
                    2682,
                    3593
                ],
                [
                    2682,
                    3545
                ],
                [
                    2639,
                    3545
                ]
            ],
            [
                [
                    2637,
                    3443
                ],
                [
                    2637,
                    3494
                ],
                [
                    2680,
                    3494
                ],
                [
                    2680,
                    3443
                ],
                [
                    2637,
                    3443
                ]
            ],
            [
                [
                    2641,
                    3340
                ],
                [
                    2641,
                    3387
                ],
                [
                    2682,
                    3387
                ],
                [
                    2682,
                    3340
                ],
                [
                    2641,
                    3340
                ]
            ],
            [
                [
                    2641,
                    3237
                ],
                [
                    2641,
                    3282
                ],
                [
                    2678,
                    3282
                ],
                [
                    2678,
                    3237
                ],
                [
                    2641,
                    3237
                ]
            ],
            [
                [
                    2641,
                    3136
                ],
                [
                    2641,
                    3175
                ],
                [
                    2682,
                    3175
                ],
                [
                    2682,
                    3136
                ],
                [
                    2641,
                    3136
                ]
            ],
            [
                [
                    2639,
                    3031
                ],
                [
                    2639,
                    3082
                ],
                [
                    2680,
                    3082
                ],
                [
                    2680,
                    3031
                ],
                [
                    2639,
                    3031
                ]
            ],
            [
                [
                    2641,
                    2917
                ],
                [
                    2641,
                    2977
                ],
                [
                    2684,
                    2977
                ],
                [
                    2684,
                    2917
                ],
                [
                    2641,
                    2917
                ]
            ],
            [
                [
                    2673,
                    2601
                ],
                [
                    2673,
                    2819
                ],
                [
                    2741,
                    2819
                ],
                [
                    2741,
                    2601
                ],
                [
                    2673,
                    2601
                ]
            ],
            [
                [
                    2702,
                    2929
                ],
                [
                    2702,
                    3343
                ],
                [
                    2742,
                    3343
                ],
                [
                    2742,
                    2929
                ],
                [
                    2702,
                    2929
                ]
            ]
        ]
    }
}